{
  "name": "GetDataArchiveCount",
  "deprecated": false,
  "security": [
    "AK"
  ],
  "protocol": "HTTP|HTTPS",
  "method": "GET|POST",
  "pathPattern": "",
  "parameters": [
    {
      "name": "OrderResultType",
      "description": "The type of the identity. Default value: AS_ADMIN.",
      "position": "Query",
      "type": "String",
      "required": false
    },
    {
      "name": "PluginType",
      "description": "The plugin type. Default value: DATA_ARCHIVE.",
      "position": "Query",
      "type": "String",
      "required": false
    },
    {
      "name": "SearchDateType",
      "description": "The time when the ticket is modified or created. The statistics of data archiving tickets are calculated based on the creation time.",
      "position": "Query",
      "type": "String",
      "required": false
    },
    {
      "name": "Tid",
      "description": "The tenant ID.\n\n>  To view the tenant ID, move the pointer over the profile picture in the upper-right corner of the Data Management (DMS) console. For more information, see [Manage DMS tenants](~~181330~~).",
      "position": "Query",
      "type": "Long",
      "required": false
    }
  ]
}