{
  "name": "ModifyAutoRepairPolicy",
  "protocol": "HTTPS",
  "method": "PUT",
  "pathPattern": "/clusters/[cluster_id]/auto_repair_policies/[policy_id]",
  "parameters": [
    {
      "name": "body",
      "position": "Body",
      "type": "String",
      "required": false
    },
    {
      "name": "cluster_id",
      "position": "Path",
      "type": "String",
      "required": false
    },
    {
      "name": "policy_id",
      "position": "Path",
      "type": "String",
      "required": false
    }
  ]
}