{
  "name": "ListInstanceSnapshot",
  "deprecated": false,
  "protocol": "HTTP|HTTPS",
  "method": "GET",
  "pathPattern": "/api/v2/instances/[InstanceId]/snapshots",
  "parameters": [
    {
      "name": "InstanceId",
      "description": "实例ID。如何获取实例ID，请参见[ListInstances](~~470439~~)。",
      "position": "Path",
      "type": "String",
      "required": true
    },
    {
      "name": "Order",
      "description": "排列顺序，取值如下：\n- Desc： 降序排列。\n- Asc： 升序排列。",
      "position": "Query",
      "type": "String",
      "required": false
    },
    {
      "name": "PageNumber",
      "description": "实例快照列表的页码。起始值为1，默认为1。",
      "position": "Query",
      "type": "Long",
      "required": false
    },
    {
      "name": "PageSize",
      "description": "分页查询时设置的每页显示的实例快照列表数量，默认为10。",
      "position": "Query",
      "type": "Long",
      "required": false
    },
    {
      "name": "SortBy",
      "description": "按排序字段gmtCreae排序。",
      "position": "Query",
      "type": "String",
      "required": false
    }
  ]
}