{
  "name": "ModifyPowerStation",
  "protocol": "HTTP|HTTPS",
  "method": "GET|POST",
  "pathPattern": "",
  "parameters": [
    {
      "name": "AlgorithmInstanceUid",
      "position": "Query",
      "type": "String",
      "required": true
    },
    {
      "name": "Description",
      "position": "Query",
      "type": "String",
      "required": false
    },
    {
      "name": "IotInstanceId",
      "position": "Query",
      "type": "String",
      "required": true
    },
    {
      "name": "PowerStationName",
      "position": "Query",
      "type": "String",
      "required": false
    },
    {
      "name": "PowerStationUid",
      "position": "Query",
      "type": "String",
      "required": true
    },
    {
      "name": "RatedPower",
      "position": "Query",
      "type": "Integer",
      "required": true
    }
  ]
}