{
  "name": "ListStorageProjectsInfo",
  "deprecated": false,
  "protocol": "HTTP|HTTPS",
  "method": "GET",
  "pathPattern": "/api/v1/observations/analysis/storage/projectsInfo",
  "parameters": [
    {
      "name": "ascOrder",
      "description": "Specifies whether to sort the results in ascending order.",
      "position": "Query",
      "type": "Boolean",
      "required": false
    },
    {
      "name": "date",
      "description": "The statistics collection date. The date is accurate to the day. The date must be in the `YYYYMMdd` format.",
      "position": "Query",
      "type": "String",
      "required": true
    },
    {
      "name": "orderColumn",
      "description": "The column to sort by. Valid values:\n\n- totalStorage\n\n- longTermStorage\n\n- lowFreqStorage\n\n- standardStorage\n\n- recycleBinStorage",
      "position": "Query",
      "type": "String",
      "required": false
    },
    {
      "name": "pageNumber",
      "description": "The page number.",
      "position": "Query",
      "type": "Long",
      "required": false
    },
    {
      "name": "pageSize",
      "description": "The number of entries to return on each page.",
      "position": "Query",
      "type": "Long",
      "required": false
    },
    {
      "name": "projectPrefix",
      "description": "The prefix of the MaxCompute project name.",
      "position": "Query",
      "type": "String",
      "required": false
    },
    {
      "name": "recentDays",
      "description": "The number of days for year-over-year comparison.",
      "position": "Query",
      "type": "Integer",
      "required": false
    },
    {
      "name": "region",
      "description": "The region ID.",
      "position": "Query",
      "type": "String",
      "required": false
    },
    {
      "name": "tenantId",
      "description": "The tenant ID. You can log on to the MaxCompute console and choose **Tenant Property** in the navigation pane on the left to view the tenant ID.",
      "position": "Query",
      "type": "String",
      "required": false
    }
  ]
}