{
  "name": "DescribeLiveDrmUsageData",
  "protocol": "HTTP|HTTPS",
  "method": "GET|POST",
  "pathPattern": "",
  "parameters": [
    {
      "name": "DomainName",
      "description": "直播域名。\n- 支持单个或批量域名查询。批量查询时多个域名用英文逗号（,）分隔。\n- 若参数为空，默认返回所有直播域名合并后的数据。",
      "position": "Query",
      "type": "String",
      "required": false
    },
    {
      "name": "EndTime",
      "description": "结束时间需大于起始时间，获日期格式按照ISO8601表示法，并使用UTC时间。格式为：YYYY-MM-DDThh:mm:ssZ",
      "position": "Query",
      "type": "String",
      "required": true
    },
    {
      "name": "Interval",
      "description": "查询数据的时间粒度。单位：秒。取值：\n- 300\n- 3600\n- 86400\n\n不传或传值不支持时，使用默认值3600秒。",
      "position": "Query",
      "type": "String",
      "required": false
    },
    {
      "name": "RegionId",
      "description": "地域ID。",
      "position": "Query",
      "type": "String",
      "required": false
    },
    {
      "name": "SplitBy",
      "description": "分组键。默认为domain,region,drm_type。可选值为domain、region、drm_type 中的一个或多个，多个使用逗号（半角）分隔。置为空或null即不区分上述键。",
      "position": "Query",
      "type": "String",
      "required": false
    },
    {
      "name": "StartTime",
      "description": "获取数据起始时间点，日期格式按照ISO8601表示法，并使用UTC时间。格式为：YYYY-MM-DDThh:mm:ssZ。最小数据粒度为5分钟",
      "position": "Query",
      "type": "String",
      "required": true
    }
  ]
}