{
  "name": "GetUserGateways",
  "protocol": "HTTP|HTTPS",
  "method": "GET|POST",
  "pathPattern": "",
  "parameters": [
    {
      "name": "PageNumber",
      "position": "Body",
      "type": "Integer",
      "required": false
    },
    {
      "name": "PageSize",
      "position": "Body",
      "type": "Integer",
      "required": false
    },
    {
      "name": "RegionId",
      "position": "Body",
      "type": "String",
      "required": false
    },
    {
      "name": "SearchKey",
      "position": "Body",
      "type": "String",
      "required": false
    }
  ]
}