{
  "name": "GetAssetsPropertyDetail",
  "protocol": "HTTP|HTTPS",
  "method": "GET|POST",
  "pathPattern": "",
  "parameters": [
    {
      "name": "Biz",
      "position": "Query",
      "type": "String",
      "required": false
    },
    {
      "name": "CurrentPage",
      "position": "Query",
      "type": "Integer",
      "required": false
    },
    {
      "name": "ItemName",
      "position": "Query",
      "type": "String",
      "required": false
    },
    {
      "name": "Lang",
      "position": "Query",
      "type": "String",
      "required": false
    },
    {
      "name": "PageSize",
      "position": "Query",
      "type": "Integer",
      "required": false
    },
    {
      "name": "Remark",
      "position": "Query",
      "type": "String",
      "required": false
    },
    {
      "name": "SearchCriteriaList",
      "position": "Query",
      "type": "Array",
      "required": false
    },
    {
      "name": "Uuid",
      "position": "Query",
      "type": "String",
      "required": false
    }
  ]
}