{
  "name": "DescribeInstanceClusterList",
  "protocol": "HTTP|HTTPS",
  "method": "GET|POST",
  "pathPattern": "",
  "parameters": [
    {
      "name": "InstanceClusterId",
      "position": "Query",
      "type": "String",
      "required": false
    },
    {
      "name": "InstanceClusterName",
      "position": "Query",
      "type": "String",
      "required": false
    },
    {
      "name": "PageNumber",
      "position": "Query",
      "type": "Integer",
      "required": false
    },
    {
      "name": "PageSize",
      "position": "Query",
      "type": "Integer",
      "required": false
    }
  ]
}