{
  "name": "DescribeVersionConfig",
  "protocol": "HTTP|HTTPS",
  "method": "GET|POST",
  "pathPattern": "",
  "parameters": [
    {
      "name": "ResourceDirectoryAccountId",
      "description": "The ID of the Alibaba Cloud account that uses Security Center.\n\n>  You can call the [GetUser](~~28681~~) operation to query the IDs of Alibaba Cloud accounts.",
      "position": "Query",
      "type": "String",
      "required": false
    },
    {
      "name": "SourceIp",
      "description": "The source IP address of the request.",
      "position": "Query",
      "type": "String",
      "required": false
    }
  ]
}