{
  "name": "GetIpamPoolNextAvailableCidr",
  "deprecated": false,
  "protocol": "HTTPS",
  "method": "GET",
  "pathPattern": "",
  "parameters": [
    {
      "name": "CidrBlock",
      "description": "需要分配的CIDR。\n\n> CidrBlock、CidrMask至少输入一个。",
      "position": "Query",
      "type": "String",
      "required": false
    },
    {
      "name": "CidrMask",
      "description": "需要分配的CIDR掩码长度。\n> CidrBlock、CidrMask至少输入一个。",
      "position": "Query",
      "type": "Integer",
      "required": false
    },
    {
      "name": "ClientToken",
      "description": "客户端Token，用于保证请求的幂等性。从您的客户端生成一个参数值，确保不同请求间该参数值唯一。ClientToken只支持ASCII字符。\n> 若您未指定，则系统自动使用API请求的RequestId作为ClientToken标识。每次API请求的RequestId不一样。",
      "position": "Query",
      "type": "String",
      "required": false
    },
    {
      "name": "IpamPoolId",
      "description": "IPAM地址池的实例ID。",
      "position": "Query",
      "type": "String",
      "required": true
    },
    {
      "name": "RegionId",
      "description": "IPAM地址池所在地域。\n> 当IPAM地址池具备地域属性时，该参数为IPAM地址池生效地域；当IPAM地址池不具备地域属性时，该参数为IPAM托管地域。",
      "position": "Query",
      "type": "String",
      "required": true
    }
  ]
}