{
  "name": "ListDeployments",
  "deprecated": false,
  "protocol": "HTTP|HTTPS",
  "method": "GET",
  "pathPattern": "/api/v2/namespaces/[namespace]/deployments",
  "parameters": [
    {
      "name": "creator",
      "description": "The ID of the user who creates the deployment.",
      "position": "Query",
      "type": "String",
      "required": false
    },
    {
      "name": "executionMode",
      "description": "The execution mode of the deployment.\n\nValid values:\n\n*   BATCH\n*   STREAMING",
      "position": "Query",
      "type": "String",
      "required": false
    },
    {
      "name": "labelKey",
      "description": "The tag key.",
      "position": "Query",
      "type": "String",
      "required": false
    },
    {
      "name": "labelValueArray",
      "description": "The tag value. Separate multiple values with semicolon (;).",
      "position": "Query",
      "type": "String",
      "required": false
    },
    {
      "name": "modifier",
      "description": "The ID of the user who modifies the deployment.",
      "position": "Query",
      "type": "String",
      "required": false
    },
    {
      "name": "name",
      "description": "The name of the deployment.",
      "position": "Query",
      "type": "String",
      "required": false
    },
    {
      "name": "namespace",
      "description": "The name of the namespace.",
      "position": "Path",
      "type": "String",
      "required": true
    },
    {
      "name": "pageIndex",
      "description": "The page number. Minimum value: 1. Default value: 1.",
      "position": "Query",
      "type": "Integer",
      "required": false
    },
    {
      "name": "pageSize",
      "description": "The number of entries per page. Valid values: 1 to 100. Default value: 10.",
      "position": "Query",
      "type": "Integer",
      "required": false
    },
    {
      "name": "sortName",
      "description": "",
      "position": "Query",
      "type": "String",
      "required": false
    },
    {
      "name": "status",
      "description": "The latest status of the deployment.\n\nValid values:\n\n*   CANCELLED\n*   FAILED\n*   RUNNING\n*   TRANSITIONING\n*   FINISHED",
      "position": "Query",
      "type": "String",
      "required": false
    },
    {
      "name": "workspace",
      "description": "The workspace ID.",
      "position": "Header",
      "type": "String",
      "required": true
    }
  ]
}