{
  "name": "DescribeDataCheckTableDetails",
  "protocol": "HTTP|HTTPS",
  "method": "GET|POST",
  "pathPattern": "",
  "parameters": [
    {
      "name": "CheckType",
      "position": "Query",
      "type": "Integer",
      "required": true
    },
    {
      "name": "DtsJobId",
      "position": "Query",
      "type": "String",
      "required": true
    },
    {
      "name": "PageNumber",
      "position": "Query",
      "type": "Integer",
      "required": false
    },
    {
      "name": "PageSize",
      "position": "Query",
      "type": "Integer",
      "required": false
    },
    {
      "name": "Status",
      "position": "Query",
      "type": "String",
      "required": false
    },
    {
      "name": "TableName",
      "position": "Query",
      "type": "String",
      "required": false
    }
  ]
}