{
  "version": "2022-12-15",
  "style": "rpc",
  "apis": {
    "ApproveOperation": {
      "title": "审批运维操作",
      "summary": "审批运维操作。",
      "deprecated": false
    },
    "ChangeNodeGroup": {
      "title": "变更节点组",
      "deprecated": false
    },
    "ChangeNodeTypes": {
      "title": "节点规格修改",
      "deprecated": false
    },
    "ChangeResourceGroup": {
      "title": "资源转组",
      "summary": "资源转组。",
      "deprecated": false
    },
    "CloseSession": {
      "title": "断开链接",
      "summary": "关闭terminal时，汇报连接断开。",
      "deprecated": false
    },
    "CreateCluster": {
      "title": "创建集群",
      "summary": "创建一个新的灵骏集群。",
      "deprecated": false
    },
    "CreateDiagnosticTask": {
      "title": "诊断任务创建接口",
      "summary": "诊断任务创建接口。",
      "deprecated": false
    },
    "CreateNetTestTask": {
      "title": "创建网络测试任务",
      "summary": "创建网络测试任务。",
      "deprecated": false
    },
    "CreateNodeGroup": {
      "title": "创建集群下的节点分组",
      "summary": "创建集群下的节点分组。",
      "deprecated": false
    },
    "CreateSession": {
      "title": "创建会话",
      "summary": "创建Web Terminal会话。",
      "deprecated": false
    },
    "CreateVsc": {
      "title": "创建Vsc",
      "summary": "创建Vsc。",
      "deprecated": false
    },
    "DeleteCluster": {
      "title": "删除集群",
      "summary": "删除灵骏集群实例。",
      "deprecated": false
    },
    "DeleteHyperNode": {
      "title": "释放超节点",
      "deprecated": false
    },
    "DeleteNode": {
      "title": "释放节点",
      "summary": "按量付费节点释放。",
      "deprecated": false
    },
    "DeleteNodeGroup": {
      "title": "删除节点分组",
      "summary": "删除节点分组。",
      "deprecated": false
    },
    "DeleteVsc": {
      "title": "删除Vsc",
      "summary": "删除Vsc。",
      "deprecated": false
    },
    "DescribeCluster": {
      "title": "查询集群",
      "summary": "查询灵骏集群详情。",
      "deprecated": false
    },
    "DescribeDiagnosticResult": {
      "title": "查询诊断任务结果",
      "summary": "诊断任务查询接口。",
      "deprecated": false
    },
    "DescribeHyperNode": {
      "title": "查询超节点详细信息接口",
      "deprecated": false
    },
    "DescribeInvocations": {
      "title": "查询命令的执行列表和状态",
      "summary": "查询运维助手命令的执行列表和状态。",
      "deprecated": false
    },
    "DescribeNetTestResult": {
      "title": "查询网络测试结果",
      "summary": "查询网络测试结果。",
      "deprecated": false
    },
    "DescribeNode": {
      "title": "查询节点",
      "summary": "查询节点列表。",
      "deprecated": false
    },
    "DescribeNodeGroup": {
      "title": "查询节点组详细信息",
      "deprecated": false
    },
    "DescribeNodeType": {
      "title": "查询节点类型详情",
      "summary": "创建Web Terminal会话。",
      "deprecated": false
    },
    "DescribeRegions": {
      "title": "查询地域列表",
      "summary": "查询地域信息列表。",
      "deprecated": false
    },
    "DescribeSendFileResults": {
      "title": "查询下发文件列表及状态",
      "summary": "查询运维助手下发文件列表及状态。",
      "deprecated": false
    },
    "DescribeTask": {
      "title": "查询任务信息",
      "summary": "查询任务详情。",
      "deprecated": false
    },
    "DescribeVsc": {
      "title": "查询Vsc",
      "summary": "获取单个Vsc详情。",
      "deprecated": false
    },
    "DescribeZones": {
      "title": "查询可用区列表",
      "summary": "可用区列表。",
      "deprecated": false
    },
    "ExtendCluster": {
      "title": "扩容集群",
      "summary": "集群扩容。",
      "deprecated": false
    },
    "ListClusterHyperNodes": {
      "title": "查询集群分组列表及分组下的超节点列表",
      "deprecated": false
    },
    "ListClusterNodes": {
      "title": "查询集群节点列表",
      "summary": "查询集群节点列表。",
      "deprecated": false
    },
    "ListClusters": {
      "title": "查询集群列表",
      "summary": "查询集群实例列表。",
      "deprecated": false
    },
    "ListDiagnosticResults": {
      "title": "诊断任务列表",
      "summary": "诊断任务列表。",
      "deprecated": false
    },
    "ListFreeHyperNodes": {
      "title": "查询可用超节点列表",
      "deprecated": false
    },
    "ListFreeNodes": {
      "title": "获取未使用节点列表",
      "summary": "查询未使用节点列表。",
      "deprecated": false
    },
    "ListHyperNodes": {
      "title": "查询超节点",
      "deprecated": false
    },
    "ListImages": {
      "title": "查询镜像列表",
      "summary": "查询用户可用的镜像列表。",
      "deprecated": false
    },
    "ListMachineNetworkInfo": {
      "title": "机型网络配置查询",
      "summary": "使用 HPNZone 和机型查询机型网络配置。",
      "deprecated": false
    },
    "ListMachineTypes": {
      "title": "查询机型列表",
      "summary": "查询用户可用的机型列表。",
      "deprecated": false
    },
    "ListNetTestResults": {
      "title": "网络列表",
      "summary": "网络测试列表。",
      "deprecated": false
    },
    "ListNodeGroups": {
      "title": "查询集群下的节点分组信息",
      "summary": "查询集群下的节点分组信息。",
      "deprecated": false
    },
    "ListSyslogs": {
      "title": "查询系统内核日志",
      "deprecated": false
    },
    "ListTagResources": {
      "title": "查询资源标签",
      "summary": "查询资源标签。",
      "deprecated": false
    },
    "ListUserClusterTypes": {
      "title": "查询用户可以使用的集群类型",
      "summary": "查询用户可以使用的集群类型。",
      "deprecated": false
    },
    "ListVscs": {
      "title": "查询Vsc列表",
      "summary": "查询Vsc列表。",
      "deprecated": false
    },
    "RebootNodes": {
      "title": "重启机器",
      "summary": "重启机器。",
      "deprecated": false
    },
    "ReimageNodes": {
      "title": "机器重装",
      "summary": "机器重装。",
      "deprecated": false
    },
    "ReportNodesStatus": {
      "title": "报告节点状态",
      "deprecated": false
    },
    "RunCommand": {
      "title": "一台或多台灵骏机器中执行一段Shell的脚本",
      "summary": "一台或多台灵骏机器中执行一段Shell的脚本。",
      "deprecated": false
    },
    "SendFile": {
      "title": "向一台或多台ECS实例下发远程文件",
      "summary": "一台或多台灵骏机器下发远程文件。",
      "deprecated": false
    },
    "ShrinkCluster": {
      "title": "集群缩容",
      "summary": "灵骏集群缩容。",
      "deprecated": false
    },
    "StopInvocation": {
      "title": "停止运维命令",
      "summary": "停止运维助手命令进程。",
      "deprecated": false
    },
    "StopNodes": {
      "title": "节点关机",
      "summary": "节点关机。",
      "deprecated": false
    },
    "TagResources": {
      "title": "资源打标签",
      "summary": "资源打用户标签。",
      "deprecated": false
    },
    "UntagResources": {
      "title": "删除资源标签",
      "summary": "删除资源自定义标签。",
      "deprecated": false
    },
    "UpdateNodeGroup": {
      "title": "更新节点分组",
      "summary": "更新节点分组。",
      "deprecated": false
    }
  }
}