{
  "name": "UpdateImage",
  "deprecated": false,
  "protocol": "HTTP|HTTPS",
  "method": "GET|POST",
  "pathPattern": "",
  "parameters": [
    {
      "name": "AcceptLanguage",
      "description": "返回信息的语言类型：\n\n- zh：中文\n- en：英文",
      "position": "Query",
      "type": "String",
      "required": false
    },
    {
      "name": "ClusterId",
      "description": "目标集群的ID。",
      "position": "Query",
      "type": "String",
      "required": true
    },
    {
      "name": "VersionCode",
      "description": "目标版本号。\n\n> 需调用GetImage接口获取可升级的版本号MaxVersionCode。",
      "position": "Query",
      "type": "String",
      "required": true
    }
  ]
}