{
  "name": "SearchKnowledges",
  "protocol": "HTTPS|HTTP",
  "method": "POST|GET",
  "parameters": [
    {
      "name": "CategoryId",
      "position": "Query",
      "type": "Long",
      "required": false,
      "hidden": false
    },
    {
      "name": "UserQuery",
      "position": "Query",
      "type": "String",
      "required": false,
      "hidden": false
    },
    {
      "name": "KnowledgeId",
      "position": "Query",
      "type": "Long",
      "required": false,
      "hidden": false
    },
    {
      "name": "KnowledgeStatus",
      "position": "Query",
      "type": "Integer",
      "required": false,
      "hidden": false
    },
    {
      "name": "KnowledgeType",
      "position": "Query",
      "type": "Integer",
      "required": false,
      "hidden": false
    },
    {
      "name": "CreateUserName",
      "position": "Query",
      "type": "String",
      "required": false,
      "hidden": false
    },
    {
      "name": "ModifyUserName",
      "position": "Query",
      "type": "String",
      "required": false,
      "hidden": false
    },
    {
      "name": "CreateTimeBegin",
      "position": "Query",
      "type": "String",
      "required": false,
      "hidden": false
    },
    {
      "name": "CreateTimeEnd",
      "position": "Query",
      "type": "String",
      "required": false,
      "hidden": false
    },
    {
      "name": "ModifyTimeBegin",
      "position": "Query",
      "type": "String",
      "required": false,
      "hidden": false
    },
    {
      "name": "ModifyTimeEnd",
      "position": "Query",
      "type": "String",
      "required": false,
      "hidden": false
    },
    {
      "name": "StartTimeBegin",
      "position": "Query",
      "type": "String",
      "required": false,
      "hidden": false
    },
    {
      "name": "StartTimeEnd",
      "position": "Query",
      "type": "String",
      "required": false,
      "hidden": false
    },
    {
      "name": "EndTimeBegin",
      "position": "Query",
      "type": "String",
      "required": false,
      "hidden": false
    },
    {
      "name": "EndTimeEnd",
      "position": "Query",
      "type": "String",
      "required": false,
      "hidden": false
    },
    {
      "name": "DataType",
      "position": "Query",
      "type": "String",
      "required": false,
      "hidden": false
    },
    {
      "name": "PageNumber",
      "position": "Query",
      "type": "Integer",
      "required": false,
      "hidden": false
    },
    {
      "name": "PageSize",
      "position": "Query",
      "type": "Integer",
      "required": false,
      "hidden": false
    }
  ]
}