{
  "name": "DescribeAutoShowListTasks",
  "protocol": "HTTP|HTTPS",
  "method": "GET|POST",
  "pathPattern": "",
  "parameters": [
    {
      "name": "CasterId",
      "description": "The ID of the production studio for which you want to query scheduled tasks.\n\n>  If the scheduled tasks were created by calling the [InitializeAutoShowListTask](~~2848056~~) operation, check the value of the response parameter CasterId to obtain the ID. If you do not specify this parameter, the system queries all the scheduled tasks that belong to the user specified by the OwnerId parameter.",
      "position": "Query",
      "type": "String",
      "required": false
    },
    {
      "name": "RegionId",
      "description": "",
      "position": "Query",
      "type": "String",
      "required": false
    }
  ]
}