{
  "version": "2019-03-15",
  "style": "rpc",
  "apis": {
    "CreateFlow": {
      "title": "CreateFlow",
      "summary": "Creates a flow.",
      "deprecated": false
    },
    "CreateSchedule": {
      "title": "CreateSchedule",
      "summary": "Creates a time-based schedule.",
      "deprecated": false
    },
    "DeleteFlow": {
      "title": "DeleteFlow",
      "summary": "Deletes an existing flow.",
      "deprecated": false
    },
    "DeleteSchedule": {
      "title": "DeleteSchedule",
      "summary": "Deletes a time-based schedule.",
      "deprecated": false
    },
    "DescribeExecution": {
      "title": "DescribeExecution",
      "summary": "Queries an execution in a flow. The long polling mode is supported. The maximum waiting period for long polling depends on the value of the WaitTimeSeconds parameter.",
      "deprecated": false
    },
    "DescribeFlow": {
      "title": "DescribeFlow",
      "summary": "Queries the information about a flow.",
      "deprecated": false
    },
    "DescribeSchedule": {
      "title": "DescribeSchedule",
      "summary": "Queries the detailed information about a time-based schedule.",
      "deprecated": false
    },
    "GetExecutionHistory": {
      "title": "GetExecutionHistory",
      "summary": "Queries the details about each step in an execution process.",
      "deprecated": false
    },
    "ListExecutions": {
      "title": "ListExecutions",
      "summary": "Queries all historical executions of a flow.",
      "deprecated": false
    },
    "ListFlows": {
      "title": "ListFlows",
      "summary": "Queries a list of flows.",
      "deprecated": false
    },
    "ListSchedules": {
      "title": "ListSchedules",
      "summary": "Queries time-based schedules in a flow.",
      "deprecated": false
    },
    "ReportTaskFailed": {
      "title": "ReportTaskFailed",
      "summary": "Reports a failed task.",
      "deprecated": false
    },
    "ReportTaskSucceeded": {
      "title": "ReportTaskSucceeded",
      "summary": "Reports a successful task.",
      "deprecated": false
    },
    "StartExecution": {
      "title": "StartExecution",
      "summary": "Starts the execution of a workflow.",
      "deprecated": false
    },
    "StartSyncExecution": {
      "title": "StartSyncExecution",
      "summary": "Synchronously starts an execution in a flow.",
      "deprecated": false
    },
    "StopExecution": {
      "title": "StopExecution",
      "summary": "Stops an execution that is in progress in a flow.",
      "deprecated": false
    },
    "UpdateFlow": {
      "title": "UpdateFlow",
      "summary": "Updates a flow.",
      "deprecated": false
    },
    "UpdateSchedule": {
      "title": "UpdateSchedule",
      "summary": "Updates a time-based schedule.",
      "deprecated": false
    }
  }
}