{
  "name": "DeleteAppGroup",
  "deprecated": false,
  "protocol": "HTTP|HTTPS",
  "method": "GET|POST",
  "pathPattern": "",
  "parameters": [
    {
      "name": "DeleteJobs",
      "description": "Specifies whether to delete the jobs in the application group. Valid values:\n\ntrue: deletes the jobs in the application group.\nfalse: does not delete the jobs in the application group.",
      "position": "Query",
      "type": "Boolean",
      "required": false
    },
    {
      "name": "GroupId",
      "description": "The ID of the application. You can obtain the ID of the application on the Application Management page in the SchedulerX console.",
      "position": "Query",
      "type": "String",
      "required": true
    },
    {
      "name": "Namespace",
      "description": "The ID of the namespace. You can obtain the ID of the namespace on the Namespace page in the SchedulerX console.",
      "position": "Query",
      "type": "String",
      "required": true
    },
    {
      "name": "RegionId",
      "description": "The ID of the region.",
      "position": "Query",
      "type": "String",
      "required": true
    }
  ]
}