{
  "name": "CheckBatchTableAccessPermission",
  "protocol": "HTTPS",
  "method": "POST",
  "pathPattern": "",
  "parameters": [
    {
      "name": "DbId",
      "position": "Query",
      "type": "Long",
      "required": true
    },
    {
      "name": "Logic",
      "position": "Query",
      "type": "Boolean",
      "required": false
    },
    {
      "name": "PermissionType",
      "position": "Query",
      "type": "String",
      "required": true
    },
    {
      "name": "TableNameList",
      "position": "Query",
      "type": "Json",
      "required": true
    },
    {
      "name": "Tid",
      "position": "Query",
      "type": "Long",
      "required": false
    }
  ]
}