{
  "name": "CreateNetworkAcl",
  "deprecated": false,
  "security": [
    "AK"
  ],
  "protocol": "HTTP|HTTPS",
  "method": "GET|POST",
  "pathPattern": "",
  "parameters": [
    {
      "name": "Description",
      "description": "网络ACL的描述信息。 \n\n长度为1～256个字符，不能以http://或https://开头。",
      "position": "Query",
      "type": "String",
      "required": false
    },
    {
      "name": "NetworkAclName",
      "description": "网络ACL的名称。\n\n长度为1~128个字符，不能以http://或https://开头。",
      "position": "Query",
      "type": "String",
      "required": false
    }
  ]
}