{
  "name": "JoinPipelineGroup",
  "deprecated": false,
  "security": [
    "AK"
  ],
  "protocol": "HTTP|HTTPS",
  "method": "POST",
  "pathPattern": "/organization/[organizationId]/pipelineGroups/join",
  "parameters": [
    {
      "name": "groupId",
      "description": "",
      "position": "Query",
      "type": "Long",
      "required": true
    },
    {
      "name": "organizationId",
      "description": "",
      "position": "Path",
      "type": "String",
      "required": true
    },
    {
      "name": "pipelineIds",
      "description": "",
      "position": "Query",
      "type": "String",
      "required": true
    }
  ]
}