{
  "name": "CreateSslVpnClientCert",
  "deprecated": false,
  "protocol": "HTTP|HTTPS",
  "method": "GET|POST",
  "pathPattern": "",
  "parameters": [
    {
      "name": "ClientToken",
      "description": "客户端Token，用于保证请求的幂等性。\n\n由客户端生成该参数值，要保证在不同请求间唯一，最大值不超过64个ASCII字符。\n\n> 若您未指定，则系统自动使用API请求的**RequestId**作为**ClientToken**标识。每次API请求的**RequestId**不一样。",
      "position": "Query",
      "type": "String",
      "required": false
    },
    {
      "name": "Name",
      "description": "客户端证书的名称。\n\n长度为1～100个字符，不能以`http://`或`https://`开头。",
      "position": "Query",
      "type": "String",
      "required": false
    },
    {
      "name": "RegionId",
      "description": "VPN网关所在的地域ID。 \n\n您可以通过调用[DescribeRegions](~~36063~~)接口获取地域ID。",
      "position": "Query",
      "type": "String",
      "required": true
    },
    {
      "name": "SslVpnServerId",
      "description": "SSL-VPN服务端的ID。",
      "position": "Query",
      "type": "String",
      "required": true
    }
  ]
}