{
  "name": "SwitchInstanceZoneFailOver",
  "deprecated": false,
  "protocol": "HTTPS",
  "method": "POST",
  "pathPattern": "",
  "parameters": [
    {
      "name": "InstanceId",
      "description": "The instance ID.",
      "position": "Query",
      "type": "String",
      "required": true
    },
    {
      "name": "SiteFaultTime",
      "description": "The duration for which the fault lasts. Unit: minutes.\n\nValid values:\n\n*   5\n*   10",
      "position": "Query",
      "type": "String",
      "required": false
    },
    {
      "name": "TargetZoneId",
      "description": "The ID of the destination zone.",
      "position": "Query",
      "type": "String",
      "required": false
    }
  ]
}