{
  "name": "ListRegistryNamespaces",
  "deprecated": false,
  "protocol": "HTTPS",
  "method": "GET",
  "pathPattern": "/registryNamespace",
  "parameters": [
    {
      "name": "keyword",
      "description": "搜索关键词，支持工作空间名称模糊搜索。",
      "position": "Query",
      "type": "String",
      "required": false
    },
    {
      "name": "maxResults",
      "description": "分页查询时每页行数。最大值为100。\n默认值：20",
      "position": "Query",
      "type": "Integer",
      "required": false
    },
    {
      "name": "nextToken",
      "description": "查询凭证（Token），取值为上一次API调用返回的NextToken参数值。",
      "position": "Query",
      "type": "String",
      "required": false
    },
    {
      "name": "type",
      "description": "工作空间类型。可选值：\n\n- system：公共工作空间\n\n- self：自定义工作空间\n\n- shared：共享工作空间\n\n - community：社区工作空间\n\n默认返回所有的",
      "position": "Query",
      "type": "String",
      "required": false
    }
  ]
}