{
  "name": "GetIqsUsage",
  "deprecated": false,
  "protocol": "HTTPS",
  "method": "GET",
  "pathPattern": "/linked-retrieval/linked-retrieval-admin/v1/iqs/usage",
  "parameters": [
    {
      "name": "callerId",
      "description": "",
      "position": "Query",
      "type": "String",
      "required": false
    },
    {
      "name": "endDate",
      "description": "",
      "position": "Query",
      "type": "String",
      "required": false
    },
    {
      "name": "startDate",
      "description": "",
      "position": "Query",
      "type": "String",
      "required": false
    }
  ]
}